manage.py
drive/__init__.py
drive/asgi.py
drive/settings.py
drive/urls.py
drive/wsgi.py
sample_app/init.py
sample_app/run.py
userface/__init__.py
userface/admin.py
userface/apps.py
userface/forms.py
userface/models.py
userface/tests.py
userface/urls.py
userface/views.py
userface/templates/.DS_Store
userface/templates/base_generic.html
userface/templates/css/.DS_Store
userface/templates/css/bootstrap.min.css
userface/templates/css/style.css
userface/templates/css/bootstrap/.DS_Store
userface/templates/css/bootstrap/_media.css
userface/templates/css/bootstrap/mixins/.DS_Store
userface/templates/css/bootstrap/mixins/_border-radius.css
userface/templates/css/bootstrap/mixins/_screen-reader.css
userface/templates/css/bootstrap/mixins/_visibility.css
userface/templates/css/bootstrap/utilities/_stretched-link.css
userface/templates/registration/logged_out.html
userface/templates/registration/login.html
userface/templates/registration/register.html
userface/templates/userface/addspot.html
userface/templates/userface/index.html
userface/templates/userface/register_vehicle.html
userface/templates/userface/search.html
userface/templates/userface/user_vehicle_list.html
driveways_project_cis4930_v6-0.0.8.dist-info/LICENSE.txt
driveways_project_cis4930_v6-0.0.8.dist-info/METADATA
driveways_project_cis4930_v6-0.0.8.dist-info/WHEEL
driveways_project_cis4930_v6-0.0.8.dist-info/entry_points.txt
driveways_project_cis4930_v6-0.0.8.dist-info/top_level.txt
driveways_project_cis4930_v6-0.0.8.dist-info/RECORD
